beowulf/__init__.py
beowulf/account.py
beowulf/aes.py
beowulf/amount.py
beowulf/beowulf.py
beowulf/beowulfd.py
beowulf/block.py
beowulf/blockchain.py
beowulf/cli.py
beowulf/commit.py
beowulf/converter.py
beowulf/dex.py
beowulf/instance.py
beowulf/supernode.py
beowulf/transactionbuilder.py
beowulf/utils.py
beowulf/wallet.py
beowulfbase/__init__.py
beowulfbase/account.py
beowulfbase/base58.py
beowulfbase/bip38.py
beowulfbase/chains.py
beowulfbase/dictionary.py
beowulfbase/exceptions.py
beowulfbase/extensionids.py
beowulfbase/http_client.py
beowulfbase/memo.py
beowulfbase/operationids.py
beowulfbase/operations.py
beowulfbase/storage.py
beowulfbase/transactions.py
beowulfbase/types.py
wallet_file/__init__.py
wallet_file/wallet_file.py
beowulf_python-0.0.4.dist-info/LICENSE
beowulf_python-0.0.4.dist-info/METADATA
beowulf_python-0.0.4.dist-info/WHEEL
beowulf_python-0.0.4.dist-info/entry_points.txt
beowulf_python-0.0.4.dist-info/top_level.txt
beowulf_python-0.0.4.dist-info/RECORD
